visualpython/__init__.py
visualpython/visualpython.js
visualpython/visualpython.yaml
visualpython/bin/__init__.py
visualpython/bin/visualpy
visualpython/bin/visualpy.bat
visualpython/css/__init__.py
visualpython/css/boardFrame.css
visualpython/css/mainFrame.css
visualpython/css/menuFrame.css
visualpython/css/root.css
visualpython/css/component/__init__.py
visualpython/css/component/alertModal.css
visualpython/css/component/dataSelector.css
visualpython/css/component/fileNavigation.css
visualpython/css/component/infoModal.css
visualpython/css/component/innerFuncViewer.css
visualpython/css/component/instanceEditor.css
visualpython/css/component/loadingSpinner.css
visualpython/css/component/modal.css
visualpython/css/component/multiSelector.css
visualpython/css/component/packageManager.css
visualpython/css/component/popupComponent.css
visualpython/css/component/successMessage.css
visualpython/css/m_apps/__init__.py
visualpython/css/m_apps/bind.css
visualpython/css/m_apps/file.css
visualpython/css/m_apps/frame.css
visualpython/css/m_apps/groupby.css
visualpython/css/m_apps/import.css
visualpython/css/m_apps/information.css
visualpython/css/m_apps/instance.css
visualpython/css/m_apps/markdown.css
visualpython/css/m_apps/pdf.css
visualpython/css/m_apps/profiling.css
visualpython/css/m_apps/reshape.css
visualpython/css/m_apps/snippets.css
visualpython/css/m_apps/subset.css
visualpython/css/m_apps/sweetviz.css
visualpython/css/m_apps/variable.css
visualpython/css/m_library/__init__.py
visualpython/css/m_library/libraryComponent.css
visualpython/css/m_library/numpyComponent.css
visualpython/css/m_logic/__init__.py
visualpython/css/m_logic/for.css
visualpython/css/m_ml/__init__.py
visualpython/css/m_ml/fitPredict.css
visualpython/css/m_ml/gridSearch.css
visualpython/css/m_ml/modelInfo.css
visualpython/css/m_ml/pipeline.css
visualpython/css/m_ml/saveLoad.css
visualpython/css/m_stats/__init__.py
visualpython/css/m_stats/descStats.css
visualpython/css/m_stats/probDist.css
visualpython-3.0.2.dist-info/LICENSE
visualpython-3.0.2.dist-info/METADATA
visualpython-3.0.2.dist-info/WHEEL
visualpython-3.0.2.dist-info/top_level.txt
visualpython-3.0.2.dist-info/RECORD
