Metadata-Version: 2.1
Name: visualpython
Version: 3.0.2
Summary: Visual Python is a GUI-based Python code generator, developed on the Jupyter Notebook as an extension.
Home-page: https://github.com/visualpython/visualpython
Author: Black Logic Co.,Ltd.
Author-email: blacklogic.dev@gmail.com
License: GPLv3
Keywords: VisualPython,visualpython,visual python,Visual Python,Visual,visual
Platform: Linux
Platform: Mac OS X
Platform: Windows
Requires-Python: >=3.6
License-File: LICENSE
